bwninja/__init__.py
bwninja/_version.py
bwninja/net.c
bwninja/net.py
bwninja/tui.py
bwninja/utils.py
bwninja-1.2.8.dist-info/METADATA
bwninja-1.2.8.dist-info/WHEEL
bwninja-1.2.8.dist-info/entry_points.txt
bwninja-1.2.8.dist-info/top_level.txt
bwninja-1.2.8.dist-info/RECORD
