Metadata-Version: 2.1
Name: bwninja
Version: 1.2.8
Summary: A modern replacement for iftop
Author-email: Tom Flanagan <tom@zkpq.ca>
Project-URL: Homepage, https://bwninja.zkpq.ca
Classifier: Development Status :: 4 - Beta
Classifier: Environment :: Console :: Curses
Classifier: Environment :: Console
Classifier: Intended Audience :: Developers
Classifier: Intended Audience :: End Users/Desktop
Classifier: Intended Audience :: Information Technology
Classifier: Intended Audience :: System Administrators
Classifier: Intended Audience :: Telecommunications Industry
Classifier: License :: Free For Educational Use
Classifier: License :: Free For Home Use
Classifier: License :: Free for non-commercial use
Classifier: Operating System :: POSIX :: Linux
Classifier: Programming Language :: Python :: 3
Classifier: Programming Language :: Python
Classifier: Topic :: Internet
Classifier: Topic :: System :: Monitoring
Classifier: Topic :: System :: Networking :: Monitoring
Classifier: Topic :: Utilities
Requires-Dist: blessed
Requires-Dist: bcc (!=0.1.10,>=0.26.0)
Requires-Dist: pandas
